pytest_steps/__init__.py
pytest_steps/_version.py
pytest_steps/common_mini_six.py
pytest_steps/plugin.py
pytest_steps/py.typed
pytest_steps/steps.py
pytest_steps/steps_common.py
pytest_steps/steps_generator.py
pytest_steps/steps_harvest.py
pytest_steps/steps_harvest_df_utils.py
pytest_steps/steps_parametrizer.py
pytest_steps-1.8.0.dist-info/LICENSE
pytest_steps-1.8.0.dist-info/METADATA
pytest_steps-1.8.0.dist-info/WHEEL
pytest_steps-1.8.0.dist-info/entry_points.txt
pytest_steps-1.8.0.dist-info/top_level.txt
pytest_steps-1.8.0.dist-info/RECORD
