Metadata-Version: 2.1
Name: pytest-steps
Version: 1.8.0
Summary: Create step-wise / incremental tests in pytest.
Home-page: https://github.com/smarie/python-pytest-steps
Author: Sylvain MARIE <sylvain.marie@se.com>
Maintainer: Sylvain MARIE <sylvain.marie@se.com>
License: BSD 3-Clause
Download-URL: https://github.com/smarie/python-pytest-steps/tarball/1.8.0
Keywords: pytest test step incremental decorator parametrize parameter state share result modular
Platform: UNKNOWN
Classifier: Development Status :: 5 - Production/Stable
Classifier: Intended Audience :: Developers
Classifier: License :: OSI Approved :: BSD License
Classifier: Topic :: Software Development :: Libraries :: Python Modules
Classifier: Topic :: Software Development :: Testing
Classifier: Programming Language :: Python
Classifier: Programming Language :: Python :: 2
Classifier: Programming Language :: Python :: 2.7
Classifier: Programming Language :: Python :: 3
Classifier: Programming Language :: Python :: 3.5
Classifier: Programming Language :: Python :: 3.6
Classifier: Programming Language :: Python :: 3.7
Classifier: Programming Language :: Python :: 3.8
Classifier: Framework :: Pytest
License-File: LICENSE
